libtcrlm/__init__.py
libtcrlm/bert.py
libtcrlm/config_reader.py
libtcrlm/mlm_token_prediction_projector.py
libtcrlm/self_attention_stack.py
libtcrlm/vector_representation_delegate.py
libtcrlm/schema/__init__.py
libtcrlm/schema/amino_acid.py
libtcrlm/schema/df_manipulation.py
libtcrlm/schema/exception.py
libtcrlm/schema/pmhc.py
libtcrlm/schema/tcr.py
libtcrlm/schema/tcr_pmhc_pair.py
libtcrlm/token_embedder/__init__.py
libtcrlm/token_embedder/blosum_embedding.py
libtcrlm/token_embedder/cdr3_embedder.py
libtcrlm/token_embedder/cdr_embedder.py
libtcrlm/token_embedder/one_hot_token_index_embedding.py
libtcrlm/token_embedder/simple_relative_position_embedding.py
libtcrlm/token_embedder/sin_position_embedding.py
libtcrlm/token_embedder/token_embedder.py
libtcrlm/tokeniser/__init__.py
libtcrlm/tokeniser/cdr3_tokeniser.py
libtcrlm/tokeniser/cdr_tokeniser.py
libtcrlm/tokeniser/token_indices.py
libtcrlm/tokeniser/tokeniser.py
libtcrlm-1.1.1.dist-info/licenses/LICENSE.txt
libtcrlm-1.1.1.dist-info/METADATA
libtcrlm-1.1.1.dist-info/WHEEL
libtcrlm-1.1.1.dist-info/top_level.txt
libtcrlm-1.1.1.dist-info/RECORD
